{
    "configurations": [
        {
            "name": "msvc-x64 Debug",
            "includePath": [
                "${workspaceFolder}/**",
                "${workspaceFolder}/rendershop-base/include",
                "${workspaceFolder}/rendershop-editor/include",
                "${workspaceFolder}/rendershop-pipes/include",
                "${workspaceFolder}/third party/include"
            ],
            "defines": [
                "_DEBUG",
                "DEBUG",
                "UNICODE",
                "_UNICODE"
            ],
            "windowsSdkVersion": "10.0.17763.0",
            "compilerPath": "C:/Program Files (x86)/Microsoft Visual Studio/2019/Community/VC/Tools/MSVC/14.23.28105/bin/Hostx64/x64/cl.exe",
            "cStandard": "c11",
            "cppStandard": "c++17",
            "intelliSenseMode": "msvc-x64"
        }
    ],
    "version": 4
}